aislab/__init__.py
aislab/dp_clean/__init__.py
aislab/dp_clean/miss.py
aislab/dp_clean/outs.py
aislab/dp_feng/__init__.py
aislab/dp_feng/binenc.py
aislab/dp_feng/decomp.py
aislab/dp_feng/fft.py
aislab/dp_feng/filt.py
aislab/dp_feng/nltransf.py
aislab/dp_feng/normlz.py
aislab/dp_fext/__init__.py
aislab/dp_fext/pca.py
aislab/dp_smplcrt/__init__.py
aislab/dp_smplcrt/csampl.py
aislab/dp_smplcrt/osampl.py
aislab/dp_smplcrt/usampl.py
aislab/gnrl/__init__.py
aislab/gnrl/bf.py
aislab/gnrl/measr.py
aislab/gnrl/sf.py
aislab/gnrl/tm.py
aislab/md_fsel/__init__.py
aislab/md_fsel/reglrz.py
aislab/md_fsel/swlda.py
aislab/md_fsel/swlinr.py
aislab/md_fsel/swlogr.py
aislab/md_fsel/vredct.py
aislab/md_reg/__init__.py
aislab/md_reg/glmest.py
aislab/md_reg/linest.py
aislab/md_reg/pe.py
aislab/md_reg/rreg.py
aislab/op_nlopt/__init__.py
aislab/op_nlopt/copt.py
aislab/op_nlopt/ga.py
aislab/op_nlopt/nlopt.py
aislab/op_nlopt/ord0.py
aislab/op_nlopt/ord12.py
aislab/op_nlopt/sepopt.py
aislab-0.0.1.dist-info/METADATA
aislab-0.0.1.dist-info/WHEEL
aislab-0.0.1.dist-info/top_level.txt
aislab-0.0.1.dist-info/RECORD
