Metadata-Version: 2.1
Name: aislab
Version: 0.0.1
Summary: Infrastructure code for running datascience python scripts
Home-page: UNKNOWN
Author: Alexander Efremov
Author-email: 
License: UNKNOWN
Platform: UNKNOWN
Requires-Python: >=3.6
Requires-Dist: numpy
